omicspylib/__init__.py
omicspylib/analysis/__init__.py
omicspylib/analysis/clusters.py
omicspylib/analysis/pairs/__init__.py
omicspylib/analysis/pairs/frequency_based.py
omicspylib/analysis/pairs/statistical.py
omicspylib/calculations/__init__.py
omicspylib/calculations/fold_change.py
omicspylib/calculations/ttest.py
omicspylib/datasets/__init__.py
omicspylib/datasets/abc.py
omicspylib/datasets/concat.py
omicspylib/datasets/peptides.py
omicspylib/datasets/proteins.py
omicspylib/go/__init__.py
omicspylib/go/goslim.py
omicspylib/plots/__init__.py
omicspylib/plots/density.py
omicspylib/plots/missing_values.py
omicspylib/plots/venn.py
omicspylib/plots/volcano.py
omicspylib/utils/__init__.py
omicspylib/utils/mq.py
omicspylib-0.1.0.dist-info/LICENSE
omicspylib-0.1.0.dist-info/METADATA
omicspylib-0.1.0.dist-info/WHEEL
omicspylib-0.1.0.dist-info/top_level.txt
omicspylib-0.1.0.dist-info/RECORD
