Metadata-Version: 2.1
Name: omicspylib
Version: 0.1.0
Summary: A python library for omics data analysis
Author-email: Kostas Tsolis <kostas.tsolis@dialectos.ai>
License:                                  Apache License
Project-URL: homepage, https://github.com/dialectos-ai/omicspylib
Project-URL: documentation, https://omicspylib.readthedocs.io/en/latest/index.html
Project-URL: repository, https://github.com/dialectos-ai/omicspylib
Requires-Python: >=3.9
License-File: LICENSE
Requires-Dist: numpy>=1.26.0
Requires-Dist: pandas>=2.0.0
Requires-Dist: scipy>=1.13.1
Requires-Dist: statsmodels>=0.14.0
Requires-Dist: matplotlib>=3.0.1
Requires-Dist: matplotlib-venn>=0.11.1
Requires-Dist: seaborn>=0.11.1
Requires-Dist: scikit-learn>=1.0.0
Requires-Dist: requests>=2.0.0
